<?xml version="1.0"?>
<labwc_config>
  <theme>
    <name>Universal-Lite</name>
    <cornerRadius>8</cornerRadius>
  </theme>
  <core>
    <xwayland>no</xwayland>
    <adaptiveSync>yes</adaptiveSync>
    <gap>6</gap>
  </core>
  <focus>
    <followMouse>no</followMouse>
    <raiseOnFocus>yes</raiseOnFocus>
  </focus>
  <keyboard>
    <repeatDelay>300</repeatDelay>
    <repeatRate>40</repeatRate>

    <!-- Terminal -->
    <keybind key="C-A-T">
      <action name="Execute" command="ptyxis"/>
    </keybind>

    <!-- Audio (Chromebook top row) — with OSD notification -->
    <keybind key="XF86AudioRaiseVolume">
      <action name="Execute" command="/usr/libexec/universal-lite-volume up"/>
    </keybind>
    <keybind key="XF86AudioLowerVolume">
      <action name="Execute" command="/usr/libexec/universal-lite-volume down"/>
    </keybind>
    <keybind key="XF86AudioMute">
      <action name="Execute" command="/usr/libexec/universal-lite-volume mute"/>
    </keybind>

    <!-- Brightness (Chromebook top row) — with OSD notification -->
    <keybind key="XF86MonBrightnessUp">
      <action name="Execute" command="/usr/libexec/universal-lite-brightness up"/>
    </keybind>
    <keybind key="XF86MonBrightnessDown">
      <action name="Execute" command="/usr/libexec/universal-lite-brightness down"/>
    </keybind>

    <!-- Chromebook function keys -->
    <keybind key="XF86FullScreen">
      <action name="ToggleFullscreen"/>
    </keybind>

    <!-- Screenshots -->
    <keybind key="Print">
      <action name="Execute" command="sh -c 'grim - | wl-copy'"/>
    </keybind>
    <keybind key="S-Print">
      <action name="Execute" command="sh -c 'grim -g &quot;$(slurp)&quot; - | wl-copy'"/>
    </keybind>

    <!-- Search/Super key shortcuts -->
    <keybind key="W-l">
      <action name="Execute" command="swaylock -f"/>
    </keybind>
    <keybind key="W-e">
      <action name="Execute" command="Thunar"/>
    </keybind>
    <keybind key="W-Escape">
      <action name="Execute" command="xfce4-taskmanager"/>
    </keybind>
    <keybind key="W-comma">
      <action name="Execute" command="universal-lite-settings"/>
    </keybind>
    <keybind key="W-space">
      <action name="Execute" command="universal-lite-app-menu"/>
    </keybind>

    <!-- Window management -->
    <keybind key="A-Tab">
      <action name="NextWindow"/>
    </keybind>
    <keybind key="A-S-Tab">
      <action name="PreviousWindow"/>
    </keybind>
    <keybind key="A-bracketleft">
      <action name="SnapToEdge"><direction>left</direction></action>
    </keybind>
    <keybind key="A-bracketright">
      <action name="SnapToEdge"><direction>right</direction></action>
    </keybind>
    <keybind key="A-F4">
      <action name="Close"/>
    </keybind>
    <keybind key="W-Up">
      <action name="ToggleMaximize"/>
    </keybind>
    <keybind key="W-Down">
      <action name="Iconify"/>
    </keybind>
  </keyboard>
  <!-- Mouse bindings: defining ANY mousebind replaces ALL labwc
       built-in defaults, so we must include the full set. -->
  <mouse>
    <context name="TitleBar">
      <mousebind button="Left" action="Press">
        <action name="Focus"/>
        <action name="Raise"/>
      </mousebind>
      <mousebind button="Left" action="Drag">
        <action name="Move"/>
      </mousebind>
      <mousebind button="Left" action="DoubleClick">
        <action name="ToggleMaximize"/>
      </mousebind>
      <mousebind button="Right" action="Press">
        <action name="Focus"/>
        <action name="Raise"/>
        <action name="ShowMenu" menu="client-menu"/>
      </mousebind>
    </context>
    <context name="Close">
      <mousebind button="Left" action="Click">
        <action name="Close"/>
      </mousebind>
    </context>
    <context name="Maximize">
      <mousebind button="Left" action="Click">
        <action name="ToggleMaximize"/>
      </mousebind>
    </context>
    <context name="Iconify">
      <mousebind button="Left" action="Click">
        <action name="Iconify"/>
      </mousebind>
    </context>
    <context name="Top">
      <mousebind button="Left" action="Drag"><action name="Resize"/></mousebind>
    </context>
    <context name="Bottom">
      <mousebind button="Left" action="Drag"><action name="Resize"/></mousebind>
    </context>
    <context name="Left">
      <mousebind button="Left" action="Drag"><action name="Resize"/></mousebind>
    </context>
    <context name="Right">
      <mousebind button="Left" action="Drag"><action name="Resize"/></mousebind>
    </context>
    <context name="TLCorner">
      <mousebind button="Left" action="Drag"><action name="Resize"/></mousebind>
    </context>
    <context name="TRCorner">
      <mousebind button="Left" action="Drag"><action name="Resize"/></mousebind>
    </context>
    <context name="BLCorner">
      <mousebind button="Left" action="Drag"><action name="Resize"/></mousebind>
    </context>
    <context name="BRCorner">
      <mousebind button="Left" action="Drag"><action name="Resize"/></mousebind>
    </context>
    <context name="Root">
      <mousebind button="Right" action="Press">
        <action name="ShowMenu" menu="desktop-menu"/>
      </mousebind>
    </context>
  </mouse>
  <windowSwitcher preview="yes" outlines="yes" order="focus">
    <osd show="yes" style="thumbnail" output="all" />
  </windowSwitcher>
</labwc_config>
